jst-1.10.0.dist-info/METADATA
jst-1.10.0.dist-info/WHEEL
jst/__init__.py
jst/__init__.pyi
jst/py.typed
jst/jst.cpython-36m-darwin.so
jst-1.10.0.dist-info/RECORD
