Metadata-Version: 2.1
Name: jst
Version: 1.10.0
Classifier: Intended Audience :: Developers
Classifier: Operating System :: MacOS
Classifier: Operating System :: Microsoft :: Windows
Classifier: Operating System :: POSIX :: Linux
Classifier: Programming Language :: Python :: 3
Classifier: Programming Language :: Python :: 3.10
Classifier: Programming Language :: Python :: 3.6
Classifier: Programming Language :: Python :: 3.7
Classifier: Programming Language :: Python :: 3.8
Classifier: Programming Language :: Python :: 3.9
Classifier: Programming Language :: Python :: Implementation :: CPython
Classifier: Programming Language :: Python
Classifier: Programming Language :: Rust
Summary: A tool to transpile JSON Schema into schemas for data processing
Author: kitagawa-hr <kitagawahr@gmail.com>
Author-email: kitagawa-hr <kitagawahr@gmail.com>
License: MPL-2.0
Requires-Python: >=3.6
Project-URL: Source Code, https://github.com/kitagawa-hr/jsonschema-transpiler
